{
  "automuteus": [
    { "DISCORD_BOT_TOKEN": "DISCORD_BOT_TOKEN" },
    { "HOST": "GALACTUS_HOST" },
    { "POSTGRES_USER": "POSTGRES_USER" },
    { "POSTGRES_PASS": "POSTGRES_PASS" },
    { "EMOJI_GUILD_ID": "EMOJI_GUILD_ID" },
    { "CAPTURE_TIMEOUT": "CAPTURE_TIMEOUT" },
    { "AUTOMUTEUS_LISTENING": "AUTOMUTEUS_LISTENING" },
    { "AUTOMUTEUS_GLOBAL_PREFIX": "AUTOMUTEUS_GLOBAL_PREFIX" },
    { "BASE_MAP_URL": "BASE_MAP_URL" },
    { "SLASH_COMMAND_GUILD_IDS": "SLASH_COMMAND_GUILD_IDS" },
    { "REDIS_ADDR": "AUTOMUTEUS_REDIS_ADDR" },
    { "GALACTUS_ADDR": "GALACTUS_ADDR" },
    { "POSTGRES_ADDR": "POSTGRES_ADDR" }
  ],
  "galactus": [
    { "WORKER_BOT_TOKENS": "WORKER_BOT_TOKENS" },
    { "DISCORD_BOT_TOKEN": "DISCORD_BOT_TOKEN" },
    { "BROKER_PORT": "BROKER_PORT" },
    { "REDIS_ADDR": "GALACTUS_REDIS_ADDR" },
    { "GALACTUS_PORT": "GALACTUS_PORT" }
  ]
}